MANIFEST.in
README
requirements.txt
setup.py
ajenti.plugin.session_list.egg-info/PKG-INFO
ajenti.plugin.session_list.egg-info/SOURCES.txt
ajenti.plugin.session_list.egg-info/dependency_links.txt
ajenti.plugin.session_list.egg-info/requires.txt
ajenti.plugin.session_list.egg-info/top_level.txt
ajenti_plugin_session_list/README.md
ajenti_plugin_session_list/__init__.py
ajenti_plugin_session_list/main.py
ajenti_plugin_session_list/plugin.yml
ajenti_plugin_session_list/requirements.txt
ajenti_plugin_session_list/views.py
ajenti_plugin_session_list/widget.py
ajenti_plugin_session_list/locale/app.pot
ajenti_plugin_session_list/locale/af/LC_MESSAGES/app.js
ajenti_plugin_session_list/locale/af/LC_MESSAGES/app.po
ajenti_plugin_session_list/locale/ar/LC_MESSAGES/app.js
ajenti_plugin_session_list/locale/ar/LC_MESSAGES/app.po
ajenti_plugin_session_list/locale/be/LC_MESSAGES/app.js
ajenti_plugin_session_list/locale/be/LC_MESSAGES/app.po
ajenti_plugin_session_list/locale/bg/LC_MESSAGES/app.js
ajenti_plugin_session_list/locale/bg/LC_MESSAGES/app.po
ajenti_plugin_session_list/locale/bn/LC_MESSAGES/app.js
ajenti_plugin_session_list/locale/bn/LC_MESSAGES/app.po
ajenti_plugin_session_list/locale/bs/LC_MESSAGES/app.js
ajenti_plugin_session_list/locale/bs/LC_MESSAGES/app.po
ajenti_plugin_session_list/locale/ca/LC_MESSAGES/app.js
ajenti_plugin_session_list/locale/ca/LC_MESSAGES/app.po
ajenti_plugin_session_list/locale/cs/LC_MESSAGES/app.js
ajenti_plugin_session_list/locale/cs/LC_MESSAGES/app.po
ajenti_plugin_session_list/locale/da/LC_MESSAGES/app.js
ajenti_plugin_session_list/locale/da/LC_MESSAGES/app.po
ajenti_plugin_session_list/locale/de/LC_MESSAGES/app.js
ajenti_plugin_session_list/locale/de/LC_MESSAGES/app.po
ajenti_plugin_session_list/locale/el/LC_MESSAGES/app.js
ajenti_plugin_session_list/locale/el/LC_MESSAGES/app.po
ajenti_plugin_session_list/locale/en/LC_MESSAGES/app.po
ajenti_plugin_session_list/locale/eo/LC_MESSAGES/app.js
ajenti_plugin_session_list/locale/eo/LC_MESSAGES/app.po
ajenti_plugin_session_list/locale/es-ES/LC_MESSAGES/app.js
ajenti_plugin_session_list/locale/es-ES/LC_MESSAGES/app.po
ajenti_plugin_session_list/locale/et/LC_MESSAGES/app.js
ajenti_plugin_session_list/locale/et/LC_MESSAGES/app.po
