Metadata-Version: 1.2
Name: ajenti.plugin.session-list
Version: 0.6
Summary: Session list
Home-page: https://ajenti.org
Author: Arnaud Kientz
Author-email: arnaud@linuxmuster.net
License: UNKNOWN
Platform: UNKNOWN
Requires-Python: >=3
